csspin_frontend/_run_cypress.py
csspin_frontend/cypress.py
csspin_frontend/cypress_schema.yaml
csspin_frontend/jest.py
csspin_frontend/jest_schema.yaml
csspin_frontend/jsconfig.py
csspin_frontend/jsconfig_schema.yaml
csspin_frontend/node.py
csspin_frontend/node_schema.yaml
csspin_frontend-2.3.2.dist-info/licenses/LICENSE
csspin_frontend-2.3.2.dist-info/METADATA
csspin_frontend-2.3.2.dist-info/WHEEL
csspin_frontend-2.3.2.dist-info/top_level.txt
csspin_frontend-2.3.2.dist-info/RECORD
